weblinx_browsergym/__init__.py
weblinx_browsergym/version.py
weblinx_browsergym-0.0.3.dist-info/METADATA
weblinx_browsergym-0.0.3.dist-info/WHEEL
weblinx_browsergym-0.0.3.dist-info/top_level.txt
weblinx_browsergym-0.0.3.dist-info/RECORD
